litepipe/__init__.py
litepipe/pipeline.py
litepipe/transform.py
litepipe-2.0.1.dist-info/LICENSE
litepipe-2.0.1.dist-info/METADATA
litepipe-2.0.1.dist-info/WHEEL
litepipe-2.0.1.dist-info/top_level.txt
litepipe-2.0.1.dist-info/RECORD
