Metadata-Version: 2.2
Name: litepipe
Version: 2.0.1
Summary: Lightweight Python library for data pipelines
Home-page: https://github.com/tunnelWithAC/litepipe
Author: Conall Daly
Author-email: conalldalydev@gmail.com
Classifier: Programming Language :: Python :: 3
Classifier: License :: OSI Approved :: MIT License
Classifier: Operating System :: OS Independent
Requires-Python: >=3.9
License-File: LICENSE
Dynamic: author
Dynamic: author-email
Dynamic: classifier
Dynamic: description
Dynamic: description-content-type
Dynamic: home-page
Dynamic: requires-python
Dynamic: summary
